cdp/__init__.py
cdp/accessibility.py
cdp/animation.py
cdp/application_cache.py
cdp/audits.py
cdp/background_service.py
cdp/browser.py
cdp/cache_storage.py
cdp/cast.py
cdp/console.py
cdp/css.py
cdp/database.py
cdp/debugger.py
cdp/device_orientation.py
cdp/dom.py
cdp/dom_debugger.py
cdp/dom_snapshot.py
cdp/dom_storage.py
cdp/emulation.py
cdp/fetch.py
cdp/headless_experimental.py
cdp/heap_profiler.py
cdp/indexed_db.py
cdp/input_.py
cdp/inspector.py
cdp/io.py
cdp/layer_tree.py
cdp/log.py
cdp/memory.py
cdp/network.py
cdp/overlay.py
cdp/page.py
cdp/performance.py
cdp/profiler.py
cdp/py.typed
cdp/runtime.py
cdp/schema.py
cdp/security.py
cdp/service_worker.py
cdp/storage.py
cdp/system_info.py
cdp/target.py
cdp/tethering.py
cdp/tracing.py
cdp/util.py
cdp/web_audio.py
cdp/web_authn.py
chrome_devtools_protocol-0.4.0.dist-info/LICENSE
chrome_devtools_protocol-0.4.0.dist-info/WHEEL
chrome_devtools_protocol-0.4.0.dist-info/METADATA
chrome_devtools_protocol-0.4.0.dist-info/RECORD
