Metadata-Version: 2.1
Name: chrome-devtools-protocol
Version: 0.4.0
Summary: Python type wrappers for Chrome DevTools Protocol (CDP)
Home-page: https://github.com/hyperiongray/python-chrome-devtools-protocol
License: MIT
Author: Mark E. Haase
Author-email: mehaase@gmail.com
Requires-Python: >=3.7,<4.0
Classifier: Development Status :: 3 - Alpha
Classifier: Intended Audience :: Developers
Classifier: License :: OSI Approved :: MIT License
Classifier: Programming Language :: Python :: 3
Classifier: Programming Language :: Python :: 3.7
Classifier: Programming Language :: Python :: 3.8
Classifier: Topic :: Internet
Requires-Dist: deprecated (>=1.2.9,<2.0.0)
